nfpranta/add.py
nfpranta-0.1.dist-info/LICENSE
nfpranta-0.1.dist-info/METADATA
nfpranta-0.1.dist-info/WHEEL
nfpranta-0.1.dist-info/top_level.txt
nfpranta-0.1.dist-info/RECORD
