Metadata-Version: 2.1
Name: nfpranta
Version: 0.1
Summary: A simple function for mathematical operations
Home-page: https://github.com/nfpranta
Author: Nafis Fuad Pranta
Author-email: u1804053@student.cuet.ac.bd
License: UNKNOWN
Platform: UNKNOWN
Classifier: Programming Language :: Python :: 3
Classifier: License :: OSI Approved :: MIT License
Classifier: Operating System :: OS Independent
